LICENSE.txt
MANIFEST.in
README.md
setup.py
dlow/__init__.py
dlow/_dlow_core.py
dlow.egg-info/PKG-INFO
dlow.egg-info/SOURCES.txt
dlow.egg-info/dependency_links.txt
dlow.egg-info/requires.txt
dlow.egg-info/top_level.txt
dlow/post_processing/__init__.py
dlow/post_processing/file_unzipper.py
dlow/s3/__init__.py
dlow/s3/descriptor.py
dlow/s3/downloader.py