Metadata-Version: 1.1
Name: dlow
Version: 0.3.4
Summary: A library for downloading an S3 folder recursively and unzipping its contents. Extensible to other sources and post-processes.
Home-page: https://github.com/theflyingnerd/dlow
Author: Sam Galbraith
Author-email: sam.j.galbraith@gmail.com
License: MIT
Platform: UNKNOWN
Classifier: Development Status :: 4 - Beta
Classifier: Topic :: System :: Archiving
Classifier: Topic :: System :: Filesystems
Classifier: License :: OSI Approved :: MIT License
Classifier: Programming Language :: Python :: 2
Classifier: Programming Language :: Python :: 2.6
Classifier: Programming Language :: Python :: 2.7
